djangocms_popup/__init__.py
djangocms_popup/admin.py
djangocms_popup/apps.py
djangocms_popup/cms_plugins.py
djangocms_popup/cms_toolbars.py
djangocms_popup/models.py
djangocms_popup/settings.py
djangocms_popup/locale/fr/LC_MESSAGES/django.mo
djangocms_popup/locale/fr/LC_MESSAGES/django.po
djangocms_popup/migrations/0001_initial.py
djangocms_popup/migrations/0002_auto_20210602_1803.py
djangocms_popup/migrations/__init__.py
djangocms_popup/templates/popup/base.html
djangocms_popup/templates/popup/bottom_right.html
djangocms_popup-1.3.3.dist-info/AUTHORS.md
djangocms_popup-1.3.3.dist-info/LICENSE
djangocms_popup-1.3.3.dist-info/METADATA
djangocms_popup-1.3.3.dist-info/WHEEL
djangocms_popup-1.3.3.dist-info/top_level.txt
djangocms_popup-1.3.3.dist-info/RECORD
