Metadata-Version: 2.1
Name: djangocms-popup
Version: 1.3.3
Summary: DjangoCMS-popup let you create small popups that contains other plugins!
Home-page: https://gitlab.com/kapt/open-source/djangocms-popup
Author: Dev Kapt
Author-email: dev@kapt.mobi
Classifier: Environment :: Web Environment
Classifier: Framework :: Django
Classifier: Framework :: Django :: 2.2
Classifier: Framework :: Django :: 3.1
Classifier: Intended Audience :: Developers
Classifier: License :: OSI Approved :: GNU General Public License v3 (GPLv3)
Classifier: Programming Language :: Python
Classifier: Programming Language :: Python :: 3
Classifier: Topic :: Internet :: WWW/HTTP
Classifier: Topic :: Internet :: WWW/HTTP :: Dynamic Content
License-File: LICENSE
License-File: AUTHORS.md
Requires-Dist: django-cms
Requires-Dist: django-sekizai
